odoo/addons/account_move_line_manufacture_info/README.rst
odoo/addons/account_move_line_manufacture_info/__init__.py
odoo/addons/account_move_line_manufacture_info/__manifest__.py
odoo/addons/account_move_line_manufacture_info/i18n/account_move_line_manufacture_info.pot
odoo/addons/account_move_line_manufacture_info/models/__init__.py
odoo/addons/account_move_line_manufacture_info/models/account_move_line.py
odoo/addons/account_move_line_manufacture_info/models/stock_move.py
odoo/addons/account_move_line_manufacture_info/readme/CONTRIBUTORS.rst
odoo/addons/account_move_line_manufacture_info/readme/DESCRIPTION.rst
odoo/addons/account_move_line_manufacture_info/readme/USAGE.rst
odoo/addons/account_move_line_manufacture_info/security/ir.model.access.csv
odoo/addons/account_move_line_manufacture_info/static/description/icon.png
odoo/addons/account_move_line_manufacture_info/static/description/index.html
odoo/addons/account_move_line_manufacture_info/tests/__init__.py
odoo/addons/account_move_line_manufacture_info/tests/test_account_move_line_manufacture_info.py
odoo/addons/account_move_line_manufacture_info/views/account_move_line_view.xml
odoo/addons/account_move_line_manufacture_info/views/mrp_production_views.xml
odoo/addons/account_move_line_manufacture_info/views/mrp_unbuild_views.xml
odoo11_addon_account_move_line_manufacture_info-11.0.1.0.0.99.dev5.dist-info/METADATA
odoo11_addon_account_move_line_manufacture_info-11.0.1.0.0.99.dev5.dist-info/WHEEL
odoo11_addon_account_move_line_manufacture_info-11.0.1.0.0.99.dev5.dist-info/top_level.txt
odoo11_addon_account_move_line_manufacture_info-11.0.1.0.0.99.dev5.dist-info/RECORD
